django_on_chain/__init__.py
django_on_chain/exceptions.py
django_on_chain/remote_api.py
django_on_chain/test.py
django_on_chain/utils.py
django_on_chain/db/__init__.py
django_on_chain/db/atomic_wrapper.py
django_on_chain/locale/fa/LC_MESSAGES/django.mo
django_on_chain/locale/fa/LC_MESSAGES/django.po
django_on_chain/middlewares/__init__.py
django_on_chain/middlewares/locale_middleware.py
django_on_chain/middlewares/reformat_exceptions.py
django_on_chain-3.2.1.dist-info/METADATA
django_on_chain-3.2.1.dist-info/RECORD
django_on_chain-3.2.1.dist-info/WHEEL
django_on_chain-3.2.1.dist-info/top_level.txt
